pyft-0.3.0.dist-info/METADATA
pyft-0.3.0.dist-info/WHEEL
pyft-0.3.0.dist-info/entry_points.txt
pyft/__init__.py
pyft/fiberplot.py
pyft/plot.py
pyft/pyft.cpython-313-darwin.so
pyft/utils.py
pyft-0.3.0.dist-info/RECORD
